sql_traceback/__init__.py
sql_traceback/config.py
sql_traceback/context_manager.py
sql_traceback/cursors.py
sql_traceback/filter.py
sql_traceback/parser.py
sql_traceback/tests/settings.py
sql_traceback/tests/test_config.py
sql_traceback/tests/test_context_manager_django.py
sql_traceback/tests/test_context_manager_pytest.py
sql_traceback/tests/test_core_functionality.py
sql_traceback/tests/test_filter.py
sql_traceback/tests/test_matrix.py
django_traceback_in_sql-0.2.3.dist-info/licenses/LICENSE
django_traceback_in_sql-0.2.3.dist-info/WHEEL
django_traceback_in_sql-0.2.3.dist-info/METADATA
django_traceback_in_sql-0.2.3.dist-info/RECORD
