Metadata-Version: 2.4
Name: django-traceback-in-sql
Version: 0.2.3
Summary: Contextmanager for annotation the relevant stack trace to SQL queries as a comment
Keywords: debugging,django,sql,traceback
Author: Jonas Vacek
License-Expression: GPL-3.0-or-later
License-File: LICENSE
Classifier: Framework :: Django
Classifier: Framework :: Django :: 4.2
Classifier: Framework :: Django :: 5.2
Classifier: Programming Language :: Python :: 3.10
Classifier: Programming Language :: Python :: 3.11
Classifier: Programming Language :: Python :: 3.12
Classifier: Programming Language :: Python :: 3.13
Classifier: Programming Language :: Python :: 3.14
Classifier: Topic :: Utilities
Requires-Dist: django>=4.2.0
Requires-Python: >=3.10
Project-URL: Repository, https://github.com/jvacek/django-traceback-in-sql
